kivy_garden/frostedglass/__init__.py
kivy_garden/frostedglass/_version.py
kivy_garden/frostedglass/tests/test_import.py
kivy_garden.frostedglass-0.5.0.dist-info/AUTHORS.txt
kivy_garden.frostedglass-0.5.0.dist-info/LICENSE.txt
kivy_garden.frostedglass-0.5.0.dist-info/METADATA
kivy_garden.frostedglass-0.5.0.dist-info/WHEEL
kivy_garden.frostedglass-0.5.0.dist-info/top_level.txt
kivy_garden.frostedglass-0.5.0.dist-info/RECORD
